{
	"config": [
		{	
			"URL": "https://www.example.com",
			"ACTIONS": [
				{
					"ACTION": "findTable",
					"TYPE": "table",
					"XPATH": "//table"
				},
				{
					"ACTION": "click",
					"TYPE": "button",
					"XPATH": "//button"
				},
				{
					"ACTION": "click",
					"TYPE": "link",
					"XPATH": "//a"
				},
				{
					"ACTION": "scroll",
					"VALUE": "100"
				},
				{
					"ACTION": "select",
					"XPATH": "//select",
					"VALUE": "100"
				},
				{
					"ACTION": "input",
					"XPATH": "//input",
					"VALUE": "100"
				},
				{
					"ACTION": "export",
					"TYPE": "json",
					"FILENAME": "output.json"
				},
				{
					"ACTION": "export",
					"TYPE": "xlsx",
					"FILENAME": "output.xls"
				},
				{
					"ACTION": "wait",
					"VALUE": "1000"
				}
			]
		}	
	]
}
